packagecloudpoll
