Metadata-Version: 1.1
Name: packagecloud-poll
Version: 0.0.2
Summary: Polls the packagecloud.io API until a package filename is found.
Home-page: https://github.com/pwyliu/packagecloud-poll
Author: Paul Liu
Author-email: paul@ferociouspings.com
License: MIT
Keywords: packagecloud.io packagecloud packagecloud-poll packaging CI
Platform: UNKNOWN
Classifier: Development Status :: 3 - Alpha
Classifier: Intended Audience :: System Administrators
Classifier: Topic :: System :: Systems Administration
Classifier: License :: OSI Approved :: MIT License
Classifier: Programming Language :: Python :: 2.7
Classifier: Programming Language :: Python :: 2 :: Only
Classifier: Operating System :: POSIX :: Linux
Classifier: Operating System :: MacOS :: MacOS X
